sctransfer/__init__.py
sctransfer/api.py
sctransfer/api_pretrain.py
sctransfer/io.py
sctransfer/layers.py
sctransfer/loss.py
sctransfer/network.py
sctransfer/network_joint.py
sctransfer/pretrain_folder.py
sctransfer/saverx_train.py
sctransfer/train.py
sctransfer/train_joint.py
sctransfer-0.1.0.dist-info/LICENSE
sctransfer-0.1.0.dist-info/METADATA
sctransfer-0.1.0.dist-info/WHEEL
sctransfer-0.1.0.dist-info/top_level.txt
sctransfer-0.1.0.dist-info/RECORD
