Metadata-Version: 2.1
Name: sctransfer
Version: 0.1.0
Summary: Python part for scRNA-seq transfer learning denoising tool SAVER-X
Home-page: https://github.com/jingshuw/sctransfer
Author: Jingshu Wang
Author-email: wangjingshususan@gmail.com
License: GPL-3
Classifier: Programming Language :: Python :: 3
Classifier: License :: OSI Approved :: GNU General Public License v3 (GPLv3)
Classifier: Operating System :: OS Independent
Requires-Python: >=3.5
License-File: LICENSE
Requires-Dist: numpy (>=1.7)
Requires-Dist: keras (<=2.3.0,>=2.2)
Requires-Dist: tensorflow (<=2.2.0,>=2.0)
Requires-Dist: h5py
Requires-Dist: six (>=1.10.0)
Requires-Dist: scikit-learn
Requires-Dist: scanpy
Requires-Dist: anndata
Requires-Dist: pandas
